paces_calc/__init__.py
paces_calc/pace.1
paces_calc/pace.py
paces_calc/pace_formatter.py
paces_calc/pace_gui.py
paces_calc/pace_math.py
paces_calc-0.9.0.dist-info/LICENSE
paces_calc-0.9.0.dist-info/METADATA
paces_calc-0.9.0.dist-info/WHEEL
paces_calc-0.9.0.dist-info/entry_points.txt
paces_calc-0.9.0.dist-info/top_level.txt
paces_calc-0.9.0.dist-info/RECORD
