Metadata-Version: 2.1
Name: paces_calc
Version: 0.9.0
Summary: pace to different distances converter
Author-email: Vladimir Herdman <vovaherdman@gmail.com>
License: MIT
Project-URL: homepage, https://github.com/Vladimir-Herdman/Pace-Calculator.git
Project-URL: repository, https://github.com/Vladimir-Herdman/Pace-Calculator.git
Keywords: pace,distance,conversion,command line
Classifier: Development Status :: 4 - Beta
Classifier: Operating System :: OS Independent
Classifier: Programming Language :: Python :: 3
Classifier: Programming Language :: Python :: 3.9
Classifier: Programming Language :: Python :: 3.10
Classifier: Programming Language :: Python :: 3.11
Classifier: Programming Language :: Python :: 3.12
Classifier: Programming Language :: Python :: 3.13
Classifier: License :: OSI Approved :: MIT License
Requires-Python: >=3.9
License-File: LICENSE
Requires-Dist: customtkinter >=5.2.2
